odata/__init__.py
odata/action.py
odata/complextype.py
odata/connection.py
odata/context.py
odata/entity.py
odata/enumtype.py
odata/exceptions.py
odata/flags.py
odata/metadata.py
odata/navproperty.py
odata/property.py
odata/query.py
odata/reflect-templates/entity.mako
odata/reflect-templates/enum_entity.mako
odata/reflect-templates/main.mako
odata/reflect-templates/nav_property.mako
odata/reflect-templates/property.mako
odata/reflect-templates/typevar.mako
odata/reflector.py
odata/service.py
odata/state.py
odata/utils.py
python_odata-0.6.3.dist-info/LICENSE
python_odata-0.6.3.dist-info/METADATA
python_odata-0.6.3.dist-info/WHEEL
python_odata-0.6.3.dist-info/RECORD
