Metadata-Version: 2.3
Name: python-odata
Version: 0.6.3
Summary: A simple library for read/write access to OData services.
License: MIT
Author: Tuomas Mursu
Author-email: tuomas.mursu@kapsi.fi
Requires-Python: >=3.8
Classifier: License :: OSI Approved :: MIT License
Classifier: Programming Language :: Python :: 3
Classifier: Programming Language :: Python :: 3.8
Classifier: Programming Language :: Python :: 3.9
Classifier: Programming Language :: Python :: 3.10
Classifier: Programming Language :: Python :: 3.11
Classifier: Programming Language :: Python :: 3.12
Classifier: Programming Language :: Python :: 3.13
Requires-Dist: mako (>=1.2.4)
Requires-Dist: python-dateutil (>=2.8.2)
Requires-Dist: requests (>=2.32.0)
Requires-Dist: rich (>=13.3.1)
